{
  "@id": "/news",
  "@type": "Document",
  "UID": "e0fb9ee5c5cc42d386a21561a057031f",
  "allow_discussion": null,
  "blocks": {
    "a6c220c0-95fc-460b-ab28-5d8a8ee182ae": {
      "@type": "title"
    },
    "e9807c38-317f-43ea-b97e-072624cbcffa": {
      "@type": "listing",
      "headlineTag": "h2",
      "querystring": {
        "query": [
          {
            "i": "portal_type",
            "o": "plone.app.querystring.operation.selection.any",
            "v": [
              "News Item"
            ]
          }
        ],
        "sort_order": "ascending"
      },
      "variation": "default"
    },
    "ff4050ab-a7d5-43a7-b34f-d74677226369": {
      "@type": "slate"
    }
  },
  "blocks_layout": {
    "items": [
      "a6c220c0-95fc-460b-ab28-5d8a8ee182ae",
      "e9807c38-317f-43ea-b97e-072624cbcffa",
      "ff4050ab-a7d5-43a7-b34f-d74677226369"
    ]
  },
  "contributors": [],
  "created": "2025-02-02T14:27:48+00:00",
  "creators": [
    "admin"
  ],
  "description": "",
  "effective": "2025-02-02T15:34:42",
  "exclude_from_nav": false,
  "expires": null,
  "exportimport.constrains": {},
  "exportimport.conversation": [],
  "id": "news",
  "is_folderish": true,
  "language": "##DEFAULT##",
  "layout": "document_view",
  "lock": {
    "locked": false,
    "stealable": true
  },
  "modified": "2025-02-02T15:34:15+00:00",
  "preview_caption": null,
  "preview_image": null,
  "review_state": "published",
  "rights": "",
  "subjects": [],
  "title": "News",
  "type_title": "Page",
  "version": "current",
  "workflow_history": {
    "simple_publication_workflow": [
      {
        "action": null,
        "actor": "admin",
        "comments": "",
        "review_state": "private",
        "time": "2025-02-02T14:27:48+00:00"
      },
      {
        "action": "publish",
        "actor": "admin",
        "comments": "",
        "review_state": "published",
        "time": "2025-02-02T14:34:42+00:00"
      }
    ]
  },
  "working_copy": null,
  "working_copy_of": null
}
